cloudflare_images/__init__.py
cloudflare_images/config.py
cloudflare_images/field.py
cloudflare_images/service.py
cloudflare_images/storage.py
django_cloudflare_images-0.6.0.dist-info/LICENSE
django_cloudflare_images-0.6.0.dist-info/METADATA
django_cloudflare_images-0.6.0.dist-info/WHEEL
django_cloudflare_images-0.6.0.dist-info/top_level.txt
django_cloudflare_images-0.6.0.dist-info/RECORD
