Metadata-Version: 2.1
Name: django-cloudflare-images
Version: 0.6.0
Summary: Cloudflare Images integration for Django
Home-page: https://github.com/KalvadTech/django-cloudflare-images/
Author: Pierre Guillemot
Author-email: pierre@kalvad.com
License: MIT
Classifier: Framework :: Django
Classifier: Programming Language :: Python :: 3
Requires-Python: >=3
License-File: LICENSE
Requires-Dist: Django >=3
Requires-Dist: requests >=2.20.0
Provides-Extra: dev
Requires-Dist: build ==1.2.1 ; extra == 'dev'
Requires-Dist: ruff ==0.4.5 ; extra == 'dev'
Requires-Dist: tox ==4.15.0 ; extra == 'dev'
